ats_case/__init__.py
ats_case/case/__init__.py
ats_case/case/asb.py
ats_case/case/atm.py
ats_case/case/base.py
ats_case/case/command.py
ats_case/case/context.py
ats_case/case/executor.py
ats_case/case/translator.py
ats_case/common/__init__.py
ats_case/common/enum.py
ats_case/common/error.py
ats_case/entity/__init__.py
ats_case/entity/ats.py
ats_case/entity/bench.py
ats_case/entity/client.py
ats_case/entity/encrypt.py
ats_case/entity/meter.py
ats_case/manage/__init__.py
ats_case/manage/core.py
ats_case/manage/start.py
ats_case/security/__init__.py
ats_case/security/link.py
ats_case/statement/__init__.py
ats_case/statement/logic.py
ats_case/template/__init__.py
ats_case/template/testcase_v1.tmp
ats_case-2.1.83.dist-info/LICENSE
ats_case-2.1.83.dist-info/METADATA
ats_case-2.1.83.dist-info/WHEEL
ats_case-2.1.83.dist-info/top_level.txt
ats_case-2.1.83.dist-info/RECORD
