Metadata-Version: 2.1
Name: ats_case
Version: 2.1.83
Summary: Test Script Development Library
Home-page: https://gitee.com/henry9000/ats_case
Author: zhangyue
Author-email: zhangyue@techen.cn
Project-URL: Bug Tracker, https://gitee.com/henry9000/ats_case/issues
Classifier: Programming Language :: Python :: 3
Classifier: License :: OSI Approved :: MIT License
Classifier: Operating System :: OS Independent
Requires-Python: >=3.9
License-File: LICENSE
Requires-Dist: pytest
Requires-Dist: pytest-ordering
Requires-Dist: psutil
Requires-Dist: gevent
Requires-Dist: ats-base
